pysnmp_mibs/ACCOUNTING-CONTROL-MIB.py
pysnmp_mibs/ADSL-LINE-EXT-MIB.py
pysnmp_mibs/ADSL-LINE-MIB.py
pysnmp_mibs/ADSL-TC-MIB.py
pysnmp_mibs/ADSL2-LINE-MIB.py
pysnmp_mibs/ADSL2-LINE-TC-MIB.py
pysnmp_mibs/AGENTX-MIB.py
pysnmp_mibs/AGGREGATE-MIB.py
pysnmp_mibs/ALARM-MIB.py
pysnmp_mibs/ALCATEL-IND1-BASE.py
pysnmp_mibs/APM-MIB.py
pysnmp_mibs/APPC-MIB.py
pysnmp_mibs/APPLETALK-MIB.py
pysnmp_mibs/APPLICATION-MIB.py
pysnmp_mibs/APPN-DLUR-MIB.py
pysnmp_mibs/APPN-MIB.py
pysnmp_mibs/APPN-TRAP-MIB.py
pysnmp_mibs/APS-MIB.py
pysnmp_mibs/ARC-MIB.py
pysnmp_mibs/ATM-ACCOUNTING-INFORMATION-MIB.py
pysnmp_mibs/ATM-MIB.py
pysnmp_mibs/ATM-TC-MIB.py
pysnmp_mibs/ATM2-MIB.py
pysnmp_mibs/BGP4-MIB.py
pysnmp_mibs/BLDG-HVAC-MIB.py
pysnmp_mibs/BRIDGE-MIB.py
pysnmp_mibs/CHARACTER-MIB.py
pysnmp_mibs/CIRCUIT-IF-MIB.py
pysnmp_mibs/CISCO-SMI.py
pysnmp_mibs/CLNS-MIB.py
pysnmp_mibs/COFFEE-POT-MIB.py
pysnmp_mibs/COPS-CLIENT-MIB.py
pysnmp_mibs/DECNET-PHIV-MIB.py
pysnmp_mibs/DIAL-CONTROL-MIB.py
pysnmp_mibs/DIFFSERV-CONFIG-MIB.py
pysnmp_mibs/DIFFSERV-DSCP-TC.py
pysnmp_mibs/DIFFSERV-MIB.py
pysnmp_mibs/DIRECTORY-SERVER-MIB.py
pysnmp_mibs/DISMAN-EVENT-MIB.py
pysnmp_mibs/DISMAN-EXPRESSION-MIB.py
pysnmp_mibs/DISMAN-NSLOOKUP-MIB.py
pysnmp_mibs/DISMAN-PING-MIB.py
pysnmp_mibs/DISMAN-SCHEDULE-MIB.py
pysnmp_mibs/DISMAN-SCRIPT-MIB.py
pysnmp_mibs/DISMAN-TRACEROUTE-MIB.py
pysnmp_mibs/DLSW-MIB.py
pysnmp_mibs/DNS-RESOLVER-MIB.py
pysnmp_mibs/DNS-SERVER-MIB.py
pysnmp_mibs/DOCS-BPI-MIB.py
pysnmp_mibs/DOCS-BPI2-MIB.py
pysnmp_mibs/DOCS-CABLE-DEVICE-MIB.py
pysnmp_mibs/DOCS-IETF-BPI2-MIB.py
pysnmp_mibs/DOCS-IETF-CABLE-DEVICE-NOTIFICATION-MIB.py
pysnmp_mibs/DOCS-IETF-QOS-MIB.py
pysnmp_mibs/DOCS-IETF-SUBMGT-MIB.py
pysnmp_mibs/DOCS-IF-MIB.py
pysnmp_mibs/DOT12-IF-MIB.py
pysnmp_mibs/DOT12-RPTR-MIB.py
pysnmp_mibs/DOT3-EPON-MIB.py
pysnmp_mibs/DOT3-OAM-MIB.py
pysnmp_mibs/DS0-MIB.py
pysnmp_mibs/DS0BUNDLE-MIB.py
pysnmp_mibs/DS1-MIB.py
pysnmp_mibs/DS3-MIB.py
pysnmp_mibs-0.1.6.dist-info/DESCRIPTION.rst
pysnmp_mibs-0.1.6.dist-info/METADATA
pysnmp_mibs-0.1.6.dist-info/RECORD
pysnmp_mibs-0.1.6.dist-info/WHEEL
pysnmp_mibs-0.1.6.dist-info/metadata.json
pysnmp_mibs-0.1.6.dist-info/top_level.txt
pysnmp_mibs-0.1.6.dist-info/zip-safe
